softheap/__init__.py
softheap/softheap.py
softheap-0.2.dist-info/METADATA
softheap-0.2.dist-info/WHEEL
softheap-0.2.dist-info/top_level.txt
softheap-0.2.dist-info/RECORD
