Metadata-Version: 2.1
Name: softheap
Version: 0.2
Summary: Python Soft Heap Implementation
Home-page: https://github.com/alex-michael17/softheap
Author: Alex Michael
Author-email: mr17state@gmail.com
License: MIT
Platform: UNKNOWN
Classifier: Programming Language :: Python :: 3
Classifier: License :: OSI Approved :: MIT License
Classifier: Operating System :: OS Independent
